gears_at_notation
