Metadata-Version: 1.1
Name: gears-at-notation
Version: 0.2
Summary: Alternative dependencies parser for gears
Home-page: https://github.com/jjay/gears-at-notation
Author: Yasha Borevich
Author-email: j.borevich@gmail.com
License: ISC
Platform: UNKNOWN
Classifier: Development Status :: 3 - Alpha
Classifier: Intended Audience :: Developers
Classifier: License :: OSI Approved :: ISC License (ISCL)
Classifier: Operating System :: OS Independent
Classifier: Programming Language :: Python
Classifier: Programming Language :: Python :: 2.7
